finance_enums/__init__.py
finance_enums/extension.cpython-310-darwin.so
finance_enums/include/finance-enums/exchange.hpp
finance_enums/include/finance-enums/equity.hpp
finance_enums/include/finance-enums/future.hpp
finance_enums/include/finance-enums/sector-mappings.hpp
finance_enums/include/finance-enums/option.hpp
finance_enums/include/finance-enums/country.hpp
finance_enums/include/finance-enums/trading.hpp
finance_enums/include/finance-enums/sector.hpp
finance_enums/include/finance-enums/currency.hpp
finance_enums/include/finance-enums/commodity.hpp
finance_enums/include/finance-enums/finance-enums.hpp
finance_enums/include/finance-enums/security.hpp
finance_enums/include/finance-enums/instrument.hpp
finance_enums/include/finance-enums/common.hpp
finance_enums/include/finance-enums/bond.hpp
finance_enums/include/finance-enums/fund.hpp
finance_enums/include/finance-enums/python/long-enums.hpp
finance_enums/include/finance-enums/python/extension.hpp
finance_enums/include/finance-enums/helpers/exports.hpp
finance_enums/include/finance-enums/helpers/enum.hpp
finance_enums/include/finance-enums/helpers/.clang-format
finance_enums/tests/test_instrument.py
finance_enums/tests/test_security.py
finance_enums/tests/test_exchange.py
finance_enums/tests/test_all.py
finance_enums/tests/test_trading.py
finance_enums/tests/test_sector.py
finance_enums/tests/test_currency.py
finance_enums/tests/test_country.py
finance_enums/lib/libfinance-enums.so
finance_enums/lib/libfinance-enums-static.a
finance_enums/lib/pkgconfig/FinanceEnums.pc
finance_enums/lib/cmake/FinanceEnums/FinanceEnumsConfig.cmake
finance_enums/lib/cmake/FinanceEnums/FinanceEnumsConfigVersion.cmake
finance_enums/lib/cmake/FinanceEnums/FinanceEnumsTargets-release.cmake
finance_enums/lib/cmake/FinanceEnums/FinanceEnumsTargets.cmake
finance_enums-0.3.0.data/data/CMakeLists.txt
finance_enums-0.3.0.data/data/LICENSE
finance_enums-0.3.0.data/data/Makefile
finance_enums-0.3.0.dist-info/RECORD
finance_enums-0.3.0.dist-info/LICENSE
finance_enums-0.3.0.dist-info/WHEEL
finance_enums-0.3.0.dist-info/top_level.txt
finance_enums-0.3.0.dist-info/METADATA
