Metadata-Version: 2.1
Name: finance-enums
Version: 0.3.0
Summary: Standard Financial Enumerations
Author-email: Tim Paine <t.paine154@gmail.com>
License: Apache License
Project-URL: Repository, https://github.com/timkpaine/finance-enums
Project-URL: Homepage, https://github.com/timkpaine/finance-enums
Project-URL: Issues, https://github.com/timkpaine/finance-enums/issues
Classifier: Development Status :: 3 - Alpha
Classifier: Programming Language :: C++
Classifier: Programming Language :: Python :: Implementation :: CPython
Classifier: Programming Language :: Python :: Implementation :: PyPy
Classifier: Programming Language :: Python :: 3
Classifier: Programming Language :: Python :: 3.7
Classifier: Programming Language :: Python :: 3.8
Classifier: Programming Language :: Python :: 3.9
Classifier: Programming Language :: Python :: 3.10
Classifier: Programming Language :: Python :: 3.11
Requires-Python: >=3.7
License-File: LICENSE
Provides-Extra: develop
Requires-Dist: black (>=23) ; extra == 'develop'
Requires-Dist: bump2version ; extra == 'develop'
Requires-Dist: check-manifest ; extra == 'develop'
Requires-Dist: cibuildwheel ; extra == 'develop'
Requires-Dist: numpy ; extra == 'develop'
Requires-Dist: pybind11[global] ; extra == 'develop'
Requires-Dist: pytest ; extra == 'develop'
Requires-Dist: pytest-cov ; extra == 'develop'
Requires-Dist: pytest-sugar ; extra == 'develop'
Requires-Dist: ruff ; extra == 'develop'
Requires-Dist: scikit-build ; extra == 'develop'
Requires-Dist: twine ; extra == 'develop'
Requires-Dist: wheel ; extra == 'develop'
Provides-Extra: test
Requires-Dist: pytest ; extra == 'test'
Requires-Dist: pytest-cov ; extra == 'test'
Requires-Dist: pytest-sugar ; extra == 'test'
